uuparser/__init__.py
uuparser/arc_hybrid.py
uuparser/bilstm.py
uuparser/chuliu_edmonds.py
uuparser/decoder.py
uuparser/elmo.py
uuparser/feature_extractor.py
uuparser/mstlstm.py
uuparser/multilayer_perceptron.py
uuparser/options_manager.py
uuparser/parser.py
uuparser/utils.py
uuparser/utils/char_map.json
uuparser/utils/eval.pl
uuparser/utils/ud2.2_iso.json
uuparser/utils/ud2.2_shared_task_models-v2.json
uuparser/utils/ud_iso.json
uuparser/utils/evaluation_script/conll17_ud_eval.py
uuparser/utils/evaluation_script/weights.clas
uuparser-2.4.dist-info/LICENSE
uuparser-2.4.dist-info/METADATA
uuparser-2.4.dist-info/WHEEL
uuparser-2.4.dist-info/entry_points.txt
uuparser-2.4.dist-info/top_level.txt
uuparser-2.4.dist-info/RECORD
