Metadata-Version: 2.1
Name: uuparser
Version: 2.4
Summary: A transition-based parser for Universal Dependencies with BiLSTM word and character representations.
Home-page: UNKNOWN
Author: Uppsala NLP group
Author-email: miryam.de_lhoneux@lingfil.uu.se
License: Apache
Keywords: nlp,parsing
Platform: UNKNOWN
Requires-Python: >=3.6
Requires-Dist: dynet
Requires-Dist: h5py
Requires-Dist: loguru
Requires-Dist: numpy
Requires-Dist: tqdm
